[{"family":"MaterialIcons","fonts":[{"asset":"fonts/MaterialIcons-Regular.otf"}]},{"family":"Pretendard","fonts":[{"weight":900,"asset":"fonts/Pretendard-Black.otf"},{"weight":800,"asset":"fonts/Pretendard-ExtraBold.otf"},{"weight":700,"asset":"fonts/Pretendard-Bold.otf"},{"weight":600,"asset":"fonts/Pretendard-SemiBold.otf"},{"weight":500,"asset":"fonts/Pretendard-Medium.otf"},{"weight":400,"asset":"fonts/Pretendard-Regular.otf"},{"weight":300,"asset":"fonts/Pretendard-Light.otf"},{"weight":200,"asset":"fonts/Pretendard-Light.otf"},{"weight":100,"asset":"fonts/Pretendard-Thin.otf"}]},{"family":"Gmarket Sans","fonts":[{"weight":900,"asset":"fonts/GmarketSansBold.otf"},{"weight":800,"asset":"fonts/GmarketSansMedium.otf"},{"weight":700,"asset":"fonts/GmarketSansLight.otf"}]},{"family":"NotoSans","fonts":[{"weight":800,"asset":"fonts/NotoSansKR-Bold.otf"},{"weight":400,"asset":"fonts/NotoSansKR-Regular.otf"}]},{"family":"GangwonEdu","fonts":[{"weight":800,"asset":"fonts/GangwonEduPowerExtraBold.ttf"}]},{"family":"packages/cupertino_icons/CupertinoIcons","fonts":[{"asset":"packages/cupertino_icons/assets/CupertinoIcons.ttf"}]}]